cvlog/__init__.py
cvlog/config.py
cvlog/html_logger.py
cvlog/html_template.py
cvlog/log.py
opencv_log-1.4.0.dist-info/LICENSE
opencv_log-1.4.0.dist-info/WHEEL
opencv_log-1.4.0.dist-info/METADATA
opencv_log-1.4.0.dist-info/RECORD
