Metadata-Version: 2.1
Name: opencv-log
Version: 1.4.0
Summary: OpenCV based visual logger for debugging,logging and testing image processing code
Home-page: https://navarasu.github.io/opencv-log
License: MIT
Keywords: opencv,log,logger,debug,test,visual log
Author: Navarasu
Author-email: navarasu@outlook.com
Requires-Python: >=3.5,<4.0
Classifier: License :: OSI Approved :: MIT License
Classifier: Operating System :: OS Independent
Classifier: Programming Language :: Python :: 3
Classifier: Programming Language :: Python :: 3.5
Classifier: Programming Language :: Python :: 3.6
Classifier: Programming Language :: Python :: 3.7
Requires-Dist: opencv-python (>=3.3)
Project-URL: Repository, https://github.com/navarasu/opencv-log
